{"_type":"export","__export_format":4,"__export_date":"2020-04-15T02:18:32.930Z","__export_source":"insomnia.desktop.app:v7.1.1","resources":[{"_id":"req_0b850ef7eef84a0a8000c92b6179527c","authentication":{},"body":{"mimeType":"application/json","text":"{\n\t\"name\":\"Rodrigo Garcia\",\n\t\"email\":\"rgflsc@gmail.com\",\n\t\"password\":\"123456\"\n}"},"created":1586915216406,"description":"","headers":[{"id":"pair_5ec50efe4f764520b4b074b4df34de7e","name":"Content-Type","value":"application/json"}],"isPrivate":false,"metaSortKey":-1586915216407,"method":"POST","modified":1586916742940,"name":"Create","parameters":[],"parentId":"fld_f50dbc3e957f4b9cb6e53770a842f0b4","settingDisableRenderRequestBody":false,"settingEncodeUrl":true,"settingFollowRedirects":"global","settingRebuildPath":true,"settingSendCookies":true,"settingStoreCookies":true,"url":"{{ base_url  }}/users","_type":"request"},{"_id":"fld_f50dbc3e957f4b9cb6e53770a842f0b4","created":1586915197316,"description":"","environment":{},"environmentPropertyOrder":null,"metaSortKey":-1586915197316,"modified":1586915197316,"name":"Users","parentId":"wrk_f70ed93b53834670b947e097608b0ff0","_type":"request_group"},{"_id":"wrk_f70ed93b53834670b947e097608b0ff0","created":1586817551870,"description":"","modified":1586817551870,"name":"rocketseat_gostack_nivel02_backend","parentId":null,"_type":"workspace"},{"_id":"req_cfa01940fc9c4b878e48c8b84d8280bf","authentication":{},"body":{},"created":1586821580159,"description":"","headers":[],"isPrivate":false,"metaSortKey":-1586821580159,"method":"GET","modified":1586821592473,"name":"List","parameters":[],"parentId":"fld_279d82ac954f4f34b54b0a29b4bbe007","settingDisableRenderRequestBody":false,"settingEncodeUrl":true,"settingFollowRedirects":"global","settingRebuildPath":true,"settingSendCookies":true,"settingStoreCookies":true,"url":"{{ base_url  }}/appointments","_type":"request"},{"_id":"fld_279d82ac954f4f34b54b0a29b4bbe007","created":1586819234723,"description":"","environment":{},"environmentPropertyOrder":null,"metaSortKey":-1586819234723,"modified":1586819234723,"name":"Appointments","parentId":"wrk_f70ed93b53834670b947e097608b0ff0","_type":"request_group"},{"_id":"req_5acdee7dcabb4908accb6b2d442cc999","authentication":{},"body":{"mimeType":"application/json","text":"{\n\t\"provider_id\": \"6b0fe417-7cf8-4fc4-a648-aa31e2ac4465\",\n\t\"date\": \"{% now 'iso-8601', '' %}\"\n}"},"created":1586819250985,"description":"","headers":[{"id":"pair_162ea247f9c14cd4a2370a048e76a69e","name":"Content-Type","value":"application/json"}],"isPrivate":false,"metaSortKey":-1586819250985,"method":"POST","modified":1586916765587,"name":"Create","parameters":[],"parentId":"fld_279d82ac954f4f34b54b0a29b4bbe007","settingDisableRenderRequestBody":false,"settingEncodeUrl":true,"settingFollowRedirects":"global","settingRebuildPath":true,"settingSendCookies":true,"settingStoreCookies":true,"url":"{{ base_url  }}/appointments","_type":"request"},{"_id":"env_69160cd1ec4d6f479ef5a703ca49139ef6e3f48a","color":null,"created":1586817552049,"data":{"base_url":"http://localhost:3333"},"dataPropertyOrder":{"&":["base_url"]},"isPrivate":false,"metaSortKey":1586817552050,"modified":1586817635693,"name":"Base Environment","parentId":"wrk_f70ed93b53834670b947e097608b0ff0","_type":"environment"},{"_id":"jar_69160cd1ec4d6f479ef5a703ca49139ef6e3f48a","cookies":[],"created":1586817552057,"modified":1586817552057,"name":"Default Jar","parentId":"wrk_f70ed93b53834670b947e097608b0ff0","_type":"cookie_jar"},{"_id":"env_657ea53282cb48daa126c4a3468b1a83","color":"#7c69cb","created":1586818702571,"data":{"base_url":"http://localhost:3333"},"dataPropertyOrder":{"&":["base_url"]},"isPrivate":false,"metaSortKey":1586818702571,"modified":1586818949370,"name":"Dev","parentId":"env_69160cd1ec4d6f479ef5a703ca49139ef6e3f48a","_type":"environment"},{"_id":"env_2b14d705afe14effbc8fe92135292dcc","color":"#00ff00","created":1586818724467,"data":{"base_url":"http://localhost:3333"},"dataPropertyOrder":{"&":["base_url"]},"isPrivate":false,"metaSortKey":1586818724467,"modified":1586818737976,"name":"Production","parentId":"env_69160cd1ec4d6f479ef5a703ca49139ef6e3f48a","_type":"environment"}]}